[
    {
        "id": 1,
        "word": "Dackel",
        "level": 1,
        "solved": false
    },
    {
        "id": 2,
        "word": "Fahne",
        "level": 1,
        "solved": false
    },
    {
        "id": 3,
        "word": "Höhle",
        "level": 1,
        "solved": false
    },
    {
        "id": 4,
        "word": "Zunge",
        "level": 1,
        "solved": false
    },
    {
        "id": 5,
        "word": "Finte",
        "level": 1,
        "solved": false
    },
    {
        "id": 6,
        "word": "Lösung",
        "level": 1,
        "solved": false
    },
    {
        "id": 7,
        "word": "Ritze",
        "level": 1,
        "solved": false
    },
    {
        "id": 8,
        "word": "Politik",
        "level": 1,
        "solved": false
    },
    {
        "id": 9,
        "word": "ohne",
        "level": 1,
        "solved": false
    },
    {
        "id": 10,
        "word": "Meise",
        "level": 1,
        "solved": false
    },
    {
        "id": 11,
        "word": "loben",
        "level": 1,
        "solved": false
    },
    {
        "id": 12,
        "word": "Liebe",
        "level": 1,
        "solved": false
    },
    {
        "id": 13,
        "word": "ungut",
        "level": 1,
        "solved": false
    },
    {
        "id": 14,
        "word": "rennen",
        "level": 1,
        "solved": false
    },
    {
        "id": 15,
        "word": "Sprint",
        "level": 1,
        "solved": false
    },
    {
        "id": 16,
        "word": "Adresse",
        "level": 2,
        "solved": false
    },
    {
        "id": 17,
        "word": "Gangster",
        "level": 2,
        "solved": false
    },
    {
        "id": 18,
        "word": "Charisma",
        "level": 2,
        "solved": false
    },
    {
        "id": 19,
        "word": "Fitness",
        "level": 2,
        "solved": false
    },
    {
        "id": 20,
        "word": "Dudelsack",
        "level": 2,
        "solved": false
    },
    {
        "id": 21,
        "word": "Gitarre",
        "level": 2,
        "solved": false
    },
    {
        "id": 22,
        "word": "Joghurt/Jogurt",
        "level": 2,
        "solved": false
    },
    {
        "id": 23,
        "word": "minimal",
        "level": 2,
        "solved": false
    },
    {
        "id": 24,
        "word": "nämlich",
        "level": 2,
        "solved": false
    },
    {
        "id": 25,
        "word": "Quarzuhr",
        "level": 2,
        "solved": false
    },
    {
        "id": 26,
        "word": "komplett",
        "level": 2,
        "solved": false
    },
    {
        "id": 27,
        "word": "vielleicht",
        "level": 2,
        "solved": false
    },
    {
        "id": 28,
        "word": "Hanfsamen",
        "level": 2,
        "solved": false
    },
    {
        "id": 29,
        "word": "Masterarbeit",
        "level": 2,
        "solved": false
    },
    {
        "id": 30,
        "word": "buchstabieren",
        "level": 2,
        "solved": false
    },
    {
        "id": 31,
        "word": "googeln",
        "level": 3,
        "solved": false
    },
    {
        "id": 32,
        "word": "Empathie",
        "level": 3,
        "solved": false
    },
    {
        "id": 33,
        "word": "galoppieren",
        "level": 3,
        "solved": false
    },
    {
        "id": 34,
        "word": "Graffiti",
        "level": 3,
        "solved": false
    },
    {
        "id": 35,
        "word": "aggressiv",
        "level": 3,
        "solved": false
    },
    {
        "id": 36,
        "word": "Mobiliar",
        "level": 3,
        "solved": false
    },
    {
        "id": 37,
        "word": "Ukulele",
        "level": 3,
        "solved": false
    },
    {
        "id": 38,
        "word": "Satellit",
        "level": 3,
        "solved": false
    },
    {
        "id": 39,
        "word": "Xylophon/Xylofon",
        "level": 3,
        "solved": false
    },
    {
        "id": 40,
        "word": "Trilogie",
        "level": 3,
        "solved": false
    },
    {
        "id": 41,
        "word": "unsympathisch",
        "level": 3,
        "solved": false
    },
    {
        "id": 42,
        "word": "unentgeltlich",
        "level": 3,
        "solved": false
    },
    {
        "id": 43,
        "word": "wiederum",
        "level": 3,
        "solved": false
    },
    {
        "id": 44,
        "word": "Mathematik",
        "level": 3,
        "solved": false
    },
    {
        "id": 45,
        "word": "lynchen",
        "level": 3,
        "solved": false
    },
    {
        "id": 46,
        "word": "adäquat",
        "level": 4,
        "solved": false
    },
    {
        "id": 47,
        "word": "Portemonnaie/Portmonee",
        "level": 4,
        "solved": false
    },
    {
        "id": 48,
        "word": "Katastrophal",
        "level": 4,
        "solved": false
    },
    {
        "id": 49,
        "word": "Gratwanderung",
        "level": 4,
        "solved": false
    },
    {
        "id": 50,
        "word": "Akquise",
        "level": 4,
        "solved": false
    },
    {
        "id": 51,
        "word": "Kumulation",
        "level": 4,
        "solved": false
    },
    {
        "id": 52,
        "word": "Symmetrie",
        "level": 4,
        "solved": false
    },
    {
        "id": 53,
        "word": "Zucchini",
        "level": 4,
        "solved": false
    },
    {
        "id": 54,
        "word": "Porzellan",
        "level": 4,
        "solved": false
    },
    {
        "id": 55,
        "word": "Reling",
        "level": 4,
        "solved": false
    },
    {
        "id": 56,
        "word": "Rhetorik",
        "level": 4,
        "solved": false
    },
    {
        "id": 57,
        "word": "Resümee",
        "level": 4,
        "solved": false
    },
    {
        "id": 58,
        "word": "Rückgrat",
        "level": 4,
        "solved": false
    },
    {
        "id": 59,
        "word": "Verwandtschaft",
        "level": 4,
        "solved": false
    },
    {
        "id": 60,
        "word": "Jackett",
        "level": 4,
        "solved": false
    },
    {
        "id": 61,
        "word": "syllabieren",
        "level": 5,
        "solved": false
    },
    {
        "id": 62,
        "word": "Mitochondrium",
        "level": 5,
        "solved": false
    },
    {
        "id": 63,
        "word": "Chrysantheme",
        "level": 5,
        "solved": false
    },
    {
        "id": 64,
        "word": "Diarrhö",
        "level": 5,
        "solved": false
    },
    {
        "id": 65,
        "word": "dilettantisch",
        "level": 5,
        "solved": false
    },
    {
        "id": 66,
        "word": "Hasardeur",
        "level": 5,
        "solved": false
    },
    {
        "id": 67,
        "word": "Lappalie",
        "level": 5,
        "solved": false
    },
    {
        "id": 68,
        "word": "Ouvertüre",
        "level": 5,
        "solved": false
    },
    {
        "id": 69,
        "word": "Stracciatella",
        "level": 5,
        "solved": false
    },
    {
        "id": 70,
        "word": "applanieren",
        "level": 5,
        "solved": false
    },
    {
        "id": 71,
        "word": "Diphtherie",
        "level": 5,
        "solved": false
    },
    {
        "id": 72,
        "word": "Epikureer",
        "level": 5,
        "solved": false
    },
    {
        "id": 73,
        "word": "Mischpoche",
        "level": 5,
        "solved": false
    },
    {
        "id": 74,
        "word": "Indanthren",
        "level": 5,
        "solved": false
    },
    {
        "id": 75,
        "word": "Souterrain",
        "level": 5,
        "solved": false
    }
]